Workbook
Name DisciplineLeadTable: 'Lookup Tables'!$A$6:$B$14
Name DisciplineList: 'Lookup Tables'!$A$6:$A$14

Sheet DASHBOARD
A1: CONSTRUCTION PROJECT MANAGEMENT DASHBOARD
A2: [Site Name] · [Project Name] · [Client] · Week: 18 / 2026 · All KPI values are live Excel formulas
A4: KEY PERFORMANCE INDICATORS
A5: OVERALL PROGRESS | D5: OPEN ACTIONS | G5: OVERDUE ACTIONS | J5: OPEN / ESCALATED RISKS | M5: OPEN NCRs
A6: =IFERROR(AVERAGE('Weekly Progress'!$H$3:$H$40),0) | D6: =COUNTIF('Action Item Log'!$I$3:$I$100,"Open")+COUNTIF('Action Item Log'!$I$3:$I$100,"Overdue") | G6: =COUNTIF('Action Item Log'!$I$3:$I$100,"Overdue") | J6: =COUNTIF('Risk Register'!$M$3:$M$100,"Open")+COUNTIF('Risk Register'!$M$3:$M$100,"Escalated") | M6: =COUNTIF('NCR Quality Tracker'!$L$3:$L$100,"Open")+COUNTIF('NCR Quality Tracker'!$L$3:$L$100,"In Progress")
A7: AVERAGE(Actual%) | D7: COUNTIF: Open + Overdue | G7: COUNTIF: status=Overdue | J7: COUNTIF: Open+Escalated | M7: COUNTIF: Open+In Progress
A9: DISCIPLINE PROGRESS · Live via AVERAGEIF / COUNTIFS from Weekly Progress, Risk Register & Action Log
A10: Discipline | B10: Planned % | C10: Actual % | D10: Variance % | E10: Status | F10: Open Actions | G10: Open Risks | H10: Open NCRs | I10: SPI (Actual/Planned)
A11: Civil | B11: =IFERROR(AVERAGEIF('Weekly Progress'!$B:$B,A11,'Weekly Progress'!$G:$G),0) | C11: =IFERROR(AVERAGEIF('Weekly Progress'!$B:$B,A11,'Weekly Progress'!$H:$H),0) | D11: =C11-B11 | E11: =IF(D11>0.03,"Ahead",IF(D11<-0.03,"Behind","On Track")) | F11: =COUNTIFS('Action Item Log'!$E:$E,A11,'Action Item Log'!$I:$I,"Open")+COUNTIFS('Action Item Log'!$E:$E,A11,'Action Item Log'!$I:$I,"Overdue") | G11: =COUNTIFS('Risk Register'!$D:$D,A11,'Risk Register'!$M:$M,"Open")+COUNTIFS('Risk Register'!$D:$D,A11,'Risk Register'!$M:$M,"Escalated") | H11: =COUNTIFS('NCR Quality Tracker'!$B:$B,A11,'NCR Quality Tracker'!$L:$L,"Open")+COUNTIFS('NCR Quality Tracker'!$B:$B,A11,'NCR Quality Tracker'!$L:$L,"In Progress") | I11: =IFERROR(C11/B11,0)
A12: Structural | B12: =IFERROR(AVERAGEIF('Weekly Progress'!$B:$B,A12,'Weekly Progress'!$G:$G),0) | C12: =IFERROR(AVERAGEIF('Weekly Progress'!$B:$B,A12,'Weekly Progress'!$H:$H),0) | D12: =C12-B12 | E12: =IF(D12>0.03,"Ahead",IF(D12<-0.03,"Behind","On Track")) | F12: =COUNTIFS('Action Item Log'!$E:$E,A12,'Action Item Log'!$I:$I,"Open")+COUNTIFS('Action Item Log'!$E:$E,A12,'Action Item Log'!$I:$I,"Overdue") | G12: =COUNTIFS('Risk Register'!$D:$D,A12,'Risk Register'!$M:$M,"Open")+COUNTIFS('Risk Register'!$D:$D,A12,'Risk Register'!$M:$M,"Escalated") | H12: =COUNTIFS('NCR Quality Tracker'!$B:$B,A12,'NCR Quality Tracker'!$L:$L,"Open")+COUNTIFS('NCR Quality Tracker'!$B:$B,A12,'NCR Quality Tracker'!$L:$L,"In Progress") | I12: =IFERROR(C12/B12,0)
A13: Electrical | B13: =IFERROR(AVERAGEIF('Weekly Progress'!$B:$B,A13,'Weekly Progress'!$G:$G),0) | C13: =IFERROR(AVERAGEIF('Weekly Progress'!$B:$B,A13,'Weekly Progress'!$H:$H),0) | D13: =C13-B13 | E13: =IF(D13>0.03,"Ahead",IF(D13<-0.03,"Behind","On Track")) | F13: =COUNTIFS('Action Item Log'!$E:$E,A13,'Action Item Log'!$I:$I,"Open")+COUNTIFS('Action Item Log'!$E:$E,A13,'Action Item Log'!$I:$I,"Overdue") | G13: =COUNTIFS('Risk Register'!$D:$D,A13,'Risk Register'!$M:$M,"Open")+COUNTIFS('Risk Register'!$D:$D,A13,'Risk Register'!$M:$M,"Escalated") | H13: =COUNTIFS('NCR Quality Tracker'!$B:$B,A13,'NCR Quality Tracker'!$L:$L,"Open")+COUNTIFS('NCR Quality Tracker'!$B:$B,A13,'NCR Quality Tracker'!$L:$L,"In Progress") | I13: =IFERROR(C13/B13,0)
A14: Mechanical | B14: =IFERROR(AVERAGEIF('Weekly Progress'!$B:$B,A14,'Weekly Progress'!$G:$G),0) | C14: =IFERROR(AVERAGEIF('Weekly Progress'!$B:$B,A14,'Weekly Progress'!$H:$H),0) | D14: =C14-B14 | E14: =IF(D14>0.03,"Ahead",IF(D14<-0.03,"Behind","On Track")) | F14: =COUNTIFS('Action Item Log'!$E:$E,A14,'Action Item Log'!$I:$I,"Open")+COUNTIFS('Action Item Log'!$E:$E,A14,'Action Item Log'!$I:$I,"Overdue") | G14: =COUNTIFS('Risk Register'!$D:$D,A14,'Risk Register'!$M:$M,"Open")+COUNTIFS('Risk Register'!$D:$D,A14,'Risk Register'!$M:$M,"Escalated") | H14: =COUNTIFS('NCR Quality Tracker'!$B:$B,A14,'NCR Quality Tracker'!$L:$L,"Open")+COUNTIFS('NCR Quality Tracker'!$B:$B,A14,'NCR Quality Tracker'!$L:$L,"In Progress") | I14: =IFERROR(C14/B14,0)
A15: Instrumentation | B15: =IFERROR(AVERAGEIF('Weekly Progress'!$B:$B,A15,'Weekly Progress'!$G:$G),0) | C15: =IFERROR(AVERAGEIF('Weekly Progress'!$B:$B,A15,'Weekly Progress'!$H:$H),0) | D15: =C15-B15 | E15: =IF(D15>0.03,"Ahead",IF(D15<-0.03,"Behind","On Track")) | F15: =COUNTIFS('Action Item Log'!$E:$E,A15,'Action Item Log'!$I:$I,"Open")+COUNTIFS('Action Item Log'!$E:$E,A15,'Action Item Log'!$I:$I,"Overdue") | G15: =COUNTIFS('Risk Register'!$D:$D,A15,'Risk Register'!$M:$M,"Open")+COUNTIFS('Risk Register'!$D:$D,A15,'Risk Register'!$M:$M,"Escalated") | H15: =COUNTIFS('NCR Quality Tracker'!$B:$B,A15,'NCR Quality Tracker'!$L:$L,"Open")+COUNTIFS('NCR Quality Tracker'!$B:$B,A15,'NCR Quality Tracker'!$L:$L,"In Progress") | I15: =IFERROR(C15/B15,0)
A16: Piping | B16: =IFERROR(AVERAGEIF('Weekly Progress'!$B:$B,A16,'Weekly Progress'!$G:$G),0) | C16: =IFERROR(AVERAGEIF('Weekly Progress'!$B:$B,A16,'Weekly Progress'!$H:$H),0) | D16: =C16-B16 | E16: =IF(D16>0.03,"Ahead",IF(D16<-0.03,"Behind","On Track")) | F16: =COUNTIFS('Action Item Log'!$E:$E,A16,'Action Item Log'!$I:$I,"Open")+COUNTIFS('Action Item Log'!$E:$E,A16,'Action Item Log'!$I:$I,"Overdue") | G16: =COUNTIFS('Risk Register'!$D:$D,A16,'Risk Register'!$M:$M,"Open")+COUNTIFS('Risk Register'!$D:$D,A16,'Risk Register'!$M:$M,"Escalated") | H16: =COUNTIFS('NCR Quality Tracker'!$B:$B,A16,'NCR Quality Tracker'!$L:$L,"Open")+COUNTIFS('NCR Quality Tracker'!$B:$B,A16,'NCR Quality Tracker'!$L:$L,"In Progress") | I16: =IFERROR(C16/B16,0)
A17: HVAC | B17: =IFERROR(AVERAGEIF('Weekly Progress'!$B:$B,A17,'Weekly Progress'!$G:$G),0) | C17: =IFERROR(AVERAGEIF('Weekly Progress'!$B:$B,A17,'Weekly Progress'!$H:$H),0) | D17: =C17-B17 | E17: =IF(D17>0.03,"Ahead",IF(D17<-0.03,"Behind","On Track")) | F17: =COUNTIFS('Action Item Log'!$E:$E,A17,'Action Item Log'!$I:$I,"Open")+COUNTIFS('Action Item Log'!$E:$E,A17,'Action Item Log'!$I:$I,"Overdue") | G17: =COUNTIFS('Risk Register'!$D:$D,A17,'Risk Register'!$M:$M,"Open")+COUNTIFS('Risk Register'!$D:$D,A17,'Risk Register'!$M:$M,"Escalated") | H17: =COUNTIFS('NCR Quality Tracker'!$B:$B,A17,'NCR Quality Tracker'!$L:$L,"Open")+COUNTIFS('NCR Quality Tracker'!$B:$B,A17,'NCR Quality Tracker'!$L:$L,"In Progress") | I17: =IFERROR(C17/B17,0)
A18: Scaffolding | B18: =IFERROR(AVERAGEIF('Weekly Progress'!$B:$B,A18,'Weekly Progress'!$G:$G),0) | C18: =IFERROR(AVERAGEIF('Weekly Progress'!$B:$B,A18,'Weekly Progress'!$H:$H),0) | D18: =C18-B18 | E18: =IF(D18>0.03,"Ahead",IF(D18<-0.03,"Behind","On Track")) | F18: =COUNTIFS('Action Item Log'!$E:$E,A18,'Action Item Log'!$I:$I,"Open")+COUNTIFS('Action Item Log'!$E:$E,A18,'Action Item Log'!$I:$I,"Overdue") | G18: =COUNTIFS('Risk Register'!$D:$D,A18,'Risk Register'!$M:$M,"Open")+COUNTIFS('Risk Register'!$D:$D,A18,'Risk Register'!$M:$M,"Escalated") | H18: =COUNTIFS('NCR Quality Tracker'!$B:$B,A18,'NCR Quality Tracker'!$L:$L,"Open")+COUNTIFS('NCR Quality Tracker'!$B:$B,A18,'NCR Quality Tracker'!$L:$L,"In Progress") | I18: =IFERROR(C18/B18,0)
A20: RISK SUMMARY · COUNTIFS | G20: ACTION ITEM STATUS · COUNTIF / COUNTIFS | M20: NCR TYPE BREAKDOWN · COUNTIFS
A21: Level | B21: Total | C21: Open | D21: Escalated | E21: Closed | G21: Status | H21: Count | I21: % of Total | J21: Critical/High | K21: Med/Low | M21: NCR Type | N21: Total | O21: Open
A22: High | B22: =COUNTIF('Risk Register'!$H:$H,"High") | C22: =COUNTIFS('Risk Register'!$H:$H,"High",'Risk Register'!$M:$M,"Open") | D22: =COUNTIFS('Risk Register'!$H:$H,"High",'Risk Register'!$M:$M,"Escalated") | E22: =COUNTIFS('Risk Register'!$H:$H,"High",'Risk Register'!$M:$M,"Closed") | G22: Open | H22: =COUNTIF('Action Item Log'!$I:$I,"Open") | I22: =IFERROR(H22/COUNTA('Action Item Log'!$I$3:$I$100),0) | J22: =COUNTIFS('Action Item Log'!$I:$I,"Open",'Action Item Log'!$H:$H,"Critical")+COUNTIFS('Action Item Log'!$I:$I,"Open",'Action Item Log'!$H:$H,"High") | K22: =COUNTIFS('Action Item Log'!$I:$I,"Open",'Action Item Log'!$H:$H,"Medium")+COUNTIFS('Action Item Log'!$I:$I,"Open",'Action Item Log'!$H:$H,"Low") | M22: Material | N22: =COUNTIF('NCR Quality Tracker'!$C:$C,"Material") | O22: =COUNTIFS('NCR Quality Tracker'!$C:$C,"Material",'NCR Quality Tracker'!$L:$L,"Open")
A23: Medium | B23: =COUNTIF('Risk Register'!$H:$H,"Medium") | C23: =COUNTIFS('Risk Register'!$H:$H,"Medium",'Risk Register'!$M:$M,"Open") | D23: =COUNTIFS('Risk Register'!$H:$H,"Medium",'Risk Register'!$M:$M,"Escalated") | E23: =COUNTIFS('Risk Register'!$H:$H,"Medium",'Risk Register'!$M:$M,"Closed") | G23: In Progress | H23: =COUNTIF('Action Item Log'!$I:$I,"In Progress") | I23: =IFERROR(H23/COUNTA('Action Item Log'!$I$3:$I$100),0) | J23: =COUNTIFS('Action Item Log'!$I:$I,"In Progress",'Action Item Log'!$H:$H,"Critical")+COUNTIFS('Action Item Log'!$I:$I,"In Progress",'Action Item Log'!$H:$H,"High") | K23: =COUNTIFS('Action Item Log'!$I:$I,"In Progress",'Action Item Log'!$H:$H,"Medium")+COUNTIFS('Action Item Log'!$I:$I,"In Progress",'Action Item Log'!$H:$H,"Low") | M23: Workmanship | N23: =COUNTIF('NCR Quality Tracker'!$C:$C,"Workmanship") | O23: =COUNTIFS('NCR Quality Tracker'!$C:$C,"Workmanship",'NCR Quality Tracker'!$L:$L,"Open")
A24: Low | B24: =COUNTIF('Risk Register'!$H:$H,"Low") | C24: =COUNTIFS('Risk Register'!$H:$H,"Low",'Risk Register'!$M:$M,"Open") | D24: =COUNTIFS('Risk Register'!$H:$H,"Low",'Risk Register'!$M:$M,"Escalated") | E24: =COUNTIFS('Risk Register'!$H:$H,"Low",'Risk Register'!$M:$M,"Closed") | G24: Overdue | H24: =COUNTIF('Action Item Log'!$I:$I,"Overdue") | I24: =IFERROR(H24/COUNTA('Action Item Log'!$I$3:$I$100),0) | J24: =COUNTIFS('Action Item Log'!$I:$I,"Overdue",'Action Item Log'!$H:$H,"Critical")+COUNTIFS('Action Item Log'!$I:$I,"Overdue",'Action Item Log'!$H:$H,"High") | K24: =COUNTIFS('Action Item Log'!$I:$I,"Overdue",'Action Item Log'!$H:$H,"Medium")+COUNTIFS('Action Item Log'!$I:$I,"Overdue",'Action Item Log'!$H:$H,"Low") | M24: Installation | N24: =COUNTIF('NCR Quality Tracker'!$C:$C,"Installation") | O24: =COUNTIFS('NCR Quality Tracker'!$C:$C,"Installation",'NCR Quality Tracker'!$L:$L,"Open")
G25: Closed | H25: =COUNTIF('Action Item Log'!$I:$I,"Closed") | I25: =IFERROR(H25/COUNTA('Action Item Log'!$I$3:$I$100),0) | J25: =COUNTIFS('Action Item Log'!$I:$I,"Closed",'Action Item Log'!$H:$H,"Critical")+COUNTIFS('Action Item Log'!$I:$I,"Closed",'Action Item Log'!$H:$H,"High") | K25: =COUNTIFS('Action Item Log'!$I:$I,"Closed",'Action Item Log'!$H:$H,"Medium")+COUNTIFS('Action Item Log'!$I:$I,"Closed",'Action Item Log'!$H:$H,"Low")
A27: MONTHLY BUDGET & EARNED VALUE SUMMARY · SUMIFS multi-criteria aggregation
A28: Month | B28: Budget Hours (SUMIFS) | C28: Actual Hours (SUMIFS) | D28: Hours Var | E28: Earned Value (SUMIFS) | F28: Planned Value (SUMIFS) | G28: SV (EV−PV) | H28: CPI (EV÷PV)
A29: Feb-26 | B29: =IFERROR(SUMIFS('Monthly Report'!$C:$C,'Monthly Report'!$A:$A,A29),0) | C29: =IFERROR(SUMIFS('Monthly Report'!$D:$D,'Monthly Report'!$A:$A,A29),0) | D29: =C29-B29 | E29: =IFERROR(SUMIFS('Monthly Report'!$G:$G,'Monthly Report'!$A:$A,A29),0) | F29: =IFERROR(SUMIFS('Monthly Report'!$H:$H,'Monthly Report'!$A:$A,A29),0) | G29: =E29-F29 | H29: =IFERROR(E29/F29,0)
A30: Mar-26 | B30: =IFERROR(SUMIFS('Monthly Report'!$C:$C,'Monthly Report'!$A:$A,A30),0) | C30: =IFERROR(SUMIFS('Monthly Report'!$D:$D,'Monthly Report'!$A:$A,A30),0) | D30: =C30-B30 | E30: =IFERROR(SUMIFS('Monthly Report'!$G:$G,'Monthly Report'!$A:$A,A30),0) | F30: =IFERROR(SUMIFS('Monthly Report'!$H:$H,'Monthly Report'!$A:$A,A30),0) | G30: =E30-F30 | H30: =IFERROR(E30/F30,0)
A31: Apr-26 | B31: =IFERROR(SUMIFS('Monthly Report'!$C:$C,'Monthly Report'!$A:$A,A31),0) | C31: =IFERROR(SUMIFS('Monthly Report'!$D:$D,'Monthly Report'!$A:$A,A31),0) | D31: =C31-B31 | E31: =IFERROR(SUMIFS('Monthly Report'!$G:$G,'Monthly Report'!$A:$A,A31),0) | F31: =IFERROR(SUMIFS('Monthly Report'!$H:$H,'Monthly Report'!$A:$A,A31),0) | G31: =E31-F31 | H31: =IFERROR(E31/F31,0)
A34: VISUAL ANALYTICS · Charts refresh automatically when data changes

Sheet Weekly Progress
A1: WEEKLY PROGRESS TRACKER — Construction Site
A2: Manual entry: columns G (Planned %) and H (Actual %). Formula-driven: I (Variance = H−G) · K (Status = IF logic) · L (Responsible = XLOOKUP) — do not overwrite.
A3: ID | B3: Discipline | C3: Activity Description | D3: Location | E3: Planned Start | F3: Planned Finish | G3: Planned % ↓ enter | H3: Actual % ↓ enter | I3: Variance % =H−G | J3: Week | K3: Status =IF formula | L3: Responsible =XLOOKUP | M3: Submitted | N3: Comments
A4: WP-001 | B4: Civil | C4: Excavation — Foundation Area B3 | D4: Zone B | E4: 46091 | F4: 46132 | G4: 1 | H4: 1 | I4: =H4-G4 | J4: 18 | K4: =IF(H4>=1,"Completed",IF(G4=0,"Not Started",IF(H4-G4>0.03,"Ahead",IF(G4-H4>0.03,"Behind","On Track")))) | L4: =IFERROR(XLOOKUP(B4,'Lookup Tables'!$A$6:$A$14,'Lookup Tables'!$B$6:$B$14,"TBD"),"-") | M4: 46143
A5: WP-002 | B5: Civil | C5: Concrete Pour — Pile Caps Grid 4–7 | D5: Zone B | E5: 46113 | F5: 46140 | G5: 0.8 | H5: 0.75 | I5: =H5-G5 | J5: 18 | K5: =IF(H5>=1,"Completed",IF(G5=0,"Not Started",IF(H5-G5>0.03,"Ahead",IF(G5-H5>0.03,"Behind","On Track")))) | L5: =IFERROR(XLOOKUP(B5,'Lookup Tables'!$A$6:$A$14,'Lookup Tables'!$B$6:$B$14,"TBD"),"-") | M5: 46143
A6: WP-003 | B6: Civil | C6: Backfill & Compaction Block C | D6: Zone C | E6: 46127 | F6: 46152 | G6: 0.4 | H6: 0.35 | I6: =H6-G6 | J6: 18 | K6: =IF(H6>=1,"Completed",IF(G6=0,"Not Started",IF(H6-G6>0.03,"Ahead",IF(G6-H6>0.03,"Behind","On Track")))) | L6: =IFERROR(XLOOKUP(B6,'Lookup Tables'!$A$6:$A$14,'Lookup Tables'!$B$6:$B$14,"TBD"),"-") | M6: 46143
A7: WP-004 | B7: Structural | C7: Steel Erection — Main Frame Level 1 | D7: Building 1 | E7: 46101 | F7: 46147 | G7: 0.9 | H7: 0.95 | I7: =H7-G7 | J7: 18 | K7: =IF(H7>=1,"Completed",IF(G7=0,"Not Started",IF(H7-G7>0.03,"Ahead",IF(G7-H7>0.03,"Behind","On Track")))) | L7: =IFERROR(XLOOKUP(B7,'Lookup Tables'!$A$6:$A$14,'Lookup Tables'!$B$6:$B$14,"TBD"),"-") | M7: 46143
A8: WP-005 | B8: Structural | C8: Secondary Steelwork — Mezzanine | D8: Building 1 | E8: 46122 | F8: 46162 | G8: 0.55 | H8: 0.58 | I8: =H8-G8 | J8: 18 | K8: =IF(H8>=1,"Completed",IF(G8=0,"Not Started",IF(H8-G8>0.03,"Ahead",IF(G8-H8>0.03,"Behind","On Track")))) | L8: =IFERROR(XLOOKUP(B8,'Lookup Tables'!$A$6:$A$14,'Lookup Tables'!$B$6:$B$14,"TBD"),"-") | M8: 46143
A9: WP-006 | B9: Electrical | C9: Cable Tray Installation — HV Zone | D9: Substation | E9: 46113 | F9: 46157 | G9: 0.6 | H9: 0.55 | I9: =H9-G9 | J9: 18 | K9: =IF(H9>=1,"Completed",IF(G9=0,"Not Started",IF(H9-G9>0.03,"Ahead",IF(G9-H9>0.03,"Behind","On Track")))) | L9: =IFERROR(XLOOKUP(B9,'Lookup Tables'!$A$6:$A$14,'Lookup Tables'!$B$6:$B$14,"TBD"),"-") | M9: 46143
A10: WP-007 | B10: Electrical | C10: LV Panel Wiring — Control Room | D10: Ctrl Room | E10: 46132 | F10: 46172 | G10: 0.25 | H10: 0.2 | I10: =H10-G10 | J10: 18 | K10: =IF(H10>=1,"Completed",IF(G10=0,"Not Started",IF(H10-G10>0.03,"Ahead",IF(G10-H10>0.03,"Behind","On Track")))) | L10: =IFERROR(XLOOKUP(B10,'Lookup Tables'!$A$6:$A$14,'Lookup Tables'!$B$6:$B$14,"TBD"),"-") | M10: 46143
A11: WP-008 | B11: Mechanical | C11: Equipment Setting — Pump Skids P1–P4 | D11: Pump Hall | E11: 46117 | F11: 46152 | G11: 0.7 | H11: 0.72 | I11: =H11-G11 | J11: 18 | K11: =IF(H11>=1,"Completed",IF(G11=0,"Not Started",IF(H11-G11>0.03,"Ahead",IF(G11-H11>0.03,"Behind","On Track")))) | L11: =IFERROR(XLOOKUP(B11,'Lookup Tables'!$A$6:$A$14,'Lookup Tables'!$B$6:$B$14,"TBD"),"-") | M11: 46143
A12: WP-009 | B12: Mechanical | C12: Crane Girder Installation | D12: Warehouse | E12: 46127 | F12: 46167 | G12: 0.4 | H12: 0.38 | I12: =H12-G12 | J12: 18 | K12: =IF(H12>=1,"Completed",IF(G12=0,"Not Started",IF(H12-G12>0.03,"Ahead",IF(G12-H12>0.03,"Behind","On Track")))) | L12: =IFERROR(XLOOKUP(B12,'Lookup Tables'!$A$6:$A$14,'Lookup Tables'!$B$6:$B$14,"TBD"),"-") | M12: 46143
A13: WP-010 | B13: Instrumentation | C13: Instrument Loop Drawing Review | D13: All Areas | E13: 46106 | F13: 46142 | G13: 0.95 | H13: 0.9 | I13: =H13-G13 | J13: 18 | K13: =IF(H13>=1,"Completed",IF(G13=0,"Not Started",IF(H13-G13>0.03,"Ahead",IF(G13-H13>0.03,"Behind","On Track")))) | L13: =IFERROR(XLOOKUP(B13,'Lookup Tables'!$A$6:$A$14,'Lookup Tables'!$B$6:$B$14,"TBD"),"-") | M13: 46143
A14: WP-011 | B14: Instrumentation | C14: Field Instrument Installation Ph.1 | D14: Zone A | E14: 46132 | F14: 46188 | G14: 0.2 | H14: 0.18 | I14: =H14-G14 | J14: 18 | K14: =IF(H14>=1,"Completed",IF(G14=0,"Not Started",IF(H14-G14>0.03,"Ahead",IF(G14-H14>0.03,"Behind","On Track")))) | L14: =IFERROR(XLOOKUP(B14,'Lookup Tables'!$A$6:$A$14,'Lookup Tables'!$B$6:$B$14,"TBD"),"-") | M14: 46143
A15: WP-012 | B15: Piping | C15: Piping Spool Fabrication | D15: Fab Shop | E15: 46082 | F15: 46142 | G15: 1 | H15: 1 | I15: =H15-G15 | J15: 18 | K15: =IF(H15>=1,"Completed",IF(G15=0,"Not Started",IF(H15-G15>0.03,"Ahead",IF(G15-H15>0.03,"Behind","On Track")))) | L15: =IFERROR(XLOOKUP(B15,'Lookup Tables'!$A$6:$A$14,'Lookup Tables'!$B$6:$B$14,"TBD"),"-") | M15: 46143
... A21: WP-018 | B21: Scaffolding | C21: Scaffolding Maintenance Inspection | D21: All | E21: 46143 | F21: 46145 | G21: 1 | H21: 1 | I21: =H21-G21 | J21: 18 | K21: =IF(H21>=1,"Completed",IF(G21=0,"Not Started",IF(H21-G21>0.03,"Ahead",IF(G21-H21>0.03,"Behind","On Track")))) | L21: =IFERROR(XLOOKUP(B21,'Lookup Tables'!$A$6:$A$14,'Lookup Tables'!$B$6:$B$14,"TBD"),"-") | M21: 46143
A23: ACTIVITY PROGRESS CHART · Planned vs Actual % per Activity

Sheet Risk Register
A1: RISK REGISTER — Construction Project
A2: Formula-driven: G (Score = Prob × Impact) · H (Level = IF nested) — enter only columns E and F to set risk level automatically.
A3: Risk ID | B3: Category | C3: Risk Description | D3: Discipline | E3: Prob (1–5) | F3: Impact (1–5) | G3: Risk Score =E×F | H3: Risk Level =IF formula | I3: Mitigation Action | J3: Risk Owner | K3: Date Identified | L3: Review Date | M3: Status | N3: Comments
A4: RSK-001 | B4: Safety | C4: Working at height without valid scaffold inspection cert | D4: Scaffolding | E4: 4 | F4: 5 | G4: =E4*F4 | H4: =IF(G4=0,"-",IF(G4>=15,"High",IF(G4>=8,"Medium","Low"))) | I4: Weekly scaffold inspection; tag all approved access points | J4: K. Lindqvist | K4: 46096 | L4: 46157 | M4: Open
A5: RSK-002 | B5: Schedule | C5: Concrete delivery delays due to road restrictions | D5: Civil | E5: 3 | F5: 4 | G5: =E5*F5 | H5: =IF(G5=0,"-",IF(G5>=15,"High",IF(G5>=8,"Medium","Low"))) | I5: Pre-order extra trucks; identify alternative delivery route | J5: J. Hansen | K5: 46101 | L5: 46152 | M5: Open
A6: RSK-003 | B6: Quality | C6: Weld defects detected in structural steel connections | D6: Structural | E6: 2 | F6: 5 | G6: =E6*F6 | H6: =IF(G6=0,"-",IF(G6>=15,"High",IF(G6>=8,"Medium","Low"))) | I6: Increase NDE scope to 20%; assign dedicated QC inspector | J6: M. Berg | K6: 46113 | L6: 46162 | M6: Escalated
A7: RSK-004 | B7: Technical | C7: Instrument loop testing failure — signal noise on TI-101 | D7: Instrumentation | E7: 3 | F7: 3 | G7: =E7*F7 | H7: =IF(G7=0,"-",IF(G7>=15,"High",IF(G7>=8,"Medium","Low"))) | I7: Replace shielded cables; verify earthing configuration | J7: T. Eriksson | K7: 46117 | L7: 46147 | M7: Open
A8: RSK-005 | B8: Cost | C8: Material price escalation — copper cable +18% | D8: Electrical | E8: 3 | F8: 3 | G8: =E8*F8 | H8: =IF(G8=0,"-",IF(G8>=15,"High",IF(G8>=8,"Medium","Low"))) | I8: Lock prices via frame agreement; evaluate alternative suppliers | J8: A. Nilsen | K8: 46109 | L8: 46170 | M8: Open
A9: RSK-006 | B9: Environmental | C9: Fuel spill risk near water body — Zone C | D9: Civil | E9: 2 | F9: 4 | G9: =E9*F9 | H9: =IF(G9=0,"-",IF(G9>=15,"High",IF(G9>=8,"Medium","Low"))) | I9: Install secondary containment; daily environmental officer check | J9: K. Lindqvist | K9: 46122 | L9: 46172 | M9: Open
A10: RSK-007 | B10: Schedule | C10: Late delivery of critical pump P-201 from vendor | D10: Mechanical | E10: 4 | F10: 3 | G10: =E10*F10 | H10: =IF(G10=0,"-",IF(G10>=15,"High",IF(G10>=8,"Medium","Low"))) | I10: Expedite vendor; activate contractual penalty clause if >1 week | J10: A. Nilsen | K10: 46124 | L10: 46154 | M10: Open
A11: RSK-008 | B11: Contractual | C11: Design change — revised P&ID impacting piping route | D11: Piping | E11: 2 | F11: 3 | G11: =E11*F11 | H11: =IF(G11=0,"-",IF(G11>=15,"High",IF(G11>=8,"Medium","Low"))) | I11: Issue formal change request; update schedule and cost estimate | J11: S. Patel | K11: 46130 | L11: 46160 | M11: Open
A12: RSK-009 | B12: Safety | C12: Subcontractor personnel without site induction | D12: All | E12: 2 | F12: 3 | G12: =E12*F12 | H12: =IF(G12=0,"-",IF(G12>=15,"High",IF(G12>=8,"Medium","Low"))) | I12: Gate access control + daily induction records; revoke access on breach | J12: L. Andersen | K12: 46132 | L12: 46174 | M12: Mitigated
A13: RSK-010 | B13: Technical | C13: Fire suppression system pressure test failure | D13: Mechanical | E13: 1 | F13: 4 | G13: =E13*F13 | H13: =IF(G13=0,"-",IF(G13>=15,"High",IF(G13>=8,"Medium","Low"))) | I13: Pre-test with water; specialist commissioning team on standby | J13: A. Nilsen | K13: 46134 | L13: 46188 | M13: Open
A14: RSK-011 | B14: Quality | C14: Painting rework due to humidity beyond 85% spec | D14: Structural | E14: 2 | F14: 2 | G14: =E14*F14 | H14: =IF(G14=0,"-",IF(G14>=15,"High",IF(G14>=8,"Medium","Low"))) | I14: Monitor humidity; restrict painting to approved windows only | J14: M. Berg | K14: 46127 | L14: 46157 | M14: Mitigated
A15: RSK-012 | B15: Schedule | C15: Permit delays for HV cable route crossing | D15: Electrical | E15: 1 | F15: 2 | G15: =E15*F15 | H15: =IF(G15=0,"-",IF(G15>=15,"High",IF(G15>=8,"Medium","Low"))) | I15: Engage authority early; submit permit 4 weeks in advance | J15: M. Berg | K15: 46137 | L15: 46174 | M15: Closed
... A18: RSK-015 | B18: Environmental | C18: Noise complaint from community during night work | D18: Civil | E18: 1 | F18: 2 | G18: =E18*F18 | H18: =IF(G18=0,"-",IF(G18>=15,"High",IF(G18>=8,"Medium","Low"))) | I18: Restrict noisy ops 07:00–22:00; notify community in advance | J18: K. Lindqvist | K18: 46142 | L18: 46174 | M18: Open

Sheet Action Item Log
A1: ACTION ITEM LOG — Site Coordination Meetings
A2: F (Responsible) = VLOOKUP · N (Days Overdue) = IF(AND(≠Closed, TODAY()>DueDate), TODAY()−DueDate, "") · Status/Priority use dropdown validation
A3: Action ID | B3: Source / Meeting | C3: Date Raised | D3: Action Description | E3: Discipline | F3: Responsible =VLOOKUP | G3: Due Date | H3: Priority | I3: Status | J3: % Done | K3: Date Closed | L3: Verified By | M3: Comments | N3: Days Overdue =IF/TODAY()
A4: ACT-001 | B4: Site Coord W17 | C4: 46136 | D4: Resolve concrete pour access conflict — Civil vs Piping Zone B | E4: Civil | F4: =IFERROR(VLOOKUP(E4,'Lookup Tables'!$A$6:$B$14,2,0),"-") | G4: 46140 | H4: High | I4: Closed | J4: 1 | K4: 46139 | L4: M. Berg | N4: =IF(AND(I4<>"Closed",I4<>"On Hold",ISNUMBER(G4),TODAY()>G4),TODAY()-G4,"")
A5: ACT-002 | B5: Daily Standup W18 | C5: 46139 | D5: Submit updated cable installation schedule for approval by Project Engineer | E5: Electrical | F5: =IFERROR(VLOOKUP(E5,'Lookup Tables'!$A$6:$B$14,2,0),"-") | G5: 46142 | H5: High | I5: Closed | J5: 1 | K5: 46141 | L5: T. Eriksson | N5: =IF(AND(I5<>"Closed",I5<>"On Hold",ISNUMBER(G5),TODAY()>G5),TODAY()-G5,"")
A6: ACT-003 | B6: Quality Mtg W17 | C6: 46136 | D6: Issue corrective action for weld rejection — NCR-007 structural connections | E6: Structural | F6: =IFERROR(VLOOKUP(E6,'Lookup Tables'!$A$6:$B$14,2,0),"-") | G6: 46144 | H6: Critical | I6: In Progress | J6: 0.6 | N6: =IF(AND(I6<>"Closed",I6<>"On Hold",ISNUMBER(G6),TODAY()>G6),TODAY()-G6,"")
A7: ACT-004 | B7: Site Coord W18 | C7: 46143 | D7: Update risk register with new schedule risks from vendor delays | E7: All | F7: =IFERROR(VLOOKUP(E7,'Lookup Tables'!$A$6:$B$14,2,0),"-") | G7: 46147 | H7: Medium | I7: Open | J7: 0 | N7: =IF(AND(I7<>"Closed",I7<>"On Hold",ISNUMBER(G7),TODAY()>G7),TODAY()-G7,"")
A8: ACT-005 | B8: Client Mtg W17 | C8: 46135 | D8: Prepare monthly progress report for Client review — May 2026 | E8: All | F8: =IFERROR(VLOOKUP(E8,'Lookup Tables'!$A$6:$B$14,2,0),"-") | G8: 46149 | H8: High | I8: Open | J8: 0 | N8: =IF(AND(I8<>"Closed",I8<>"On Hold",ISNUMBER(G8),TODAY()>G8),TODAY()-G8,"")
A9: ACT-006 | B9: Daily Standup W18 | C9: 46140 | D9: Calibrate pressure gauges before hydrostatic test — Piping Line P-102 | E9: Piping | F9: =IFERROR(VLOOKUP(E9,'Lookup Tables'!$A$6:$B$14,2,0),"-") | G9: 46142 | H9: High | I9: Closed | J9: 1 | K9: 46142 | L9: A. Nilsen | N9: =IF(AND(I9<>"Closed",I9<>"On Hold",ISNUMBER(G9),TODAY()>G9),TODAY()-G9,"")
A10: ACT-007 | B10: Safety Mtg W18 | C10: 46141 | D10: Conduct emergency evacuation drill before end of May | E10: All | F10: =IFERROR(VLOOKUP(E10,'Lookup Tables'!$A$6:$B$14,2,0),"-") | G10: 46162 | H10: Medium | I10: Open | J10: 0 | L10: Coordinate HSE | N10: =IF(AND(I10<>"Closed",I10<>"On Hold",ISNUMBER(G10),TODAY()>G10),TODAY()-G10,"")
A11: ACT-008 | B11: Quality Mtg W18 | C11: 46142 | D11: Review and close outstanding punchlist items — Structural Level 1 | E11: Structural | F11: =IFERROR(VLOOKUP(E11,'Lookup Tables'!$A$6:$B$14,2,0),"-") | G11: 46151 | H11: Medium | I11: In Progress | J11: 0.3 | N11: =IF(AND(I11<>"Closed",I11<>"On Hold",ISNUMBER(G11),TODAY()>G11),TODAY()-G11,"")
A12: ACT-009 | B12: Site Coord W18 | C12: 46143 | D12: Confirm HVAC unit dimensions match building opening before delivery | E12: HVAC | F12: =IFERROR(VLOOKUP(E12,'Lookup Tables'!$A$6:$B$14,2,0),"-") | G12: 46150 | H12: High | I12: Open | J12: 0 | N12: =IF(AND(I12<>"Closed",I12<>"On Hold",ISNUMBER(G12),TODAY()>G12),TODAY()-G12,"")
A13: ACT-010 | B13: Client Mtg W17 | C13: 46135 | D13: Issue revised programme baseline incorporating scope change SCR-012 | E13: All | F13: =IFERROR(VLOOKUP(E13,'Lookup Tables'!$A$6:$B$14,2,0),"-") | G13: 46145 | H13: Critical | I13: Overdue | J13: 0.8 | L13: Awaiting design | N13: =IF(AND(I13<>"Closed",I13<>"On Hold",ISNUMBER(G13),TODAY()>G13),TODAY()-G13,"")
A14: ACT-011 | B14: Daily Standup W19 | C14: 46146 | D14: Update SharePoint tracker — weekly discipline progress inputs for W19 | E14: All | F14: =IFERROR(VLOOKUP(E14,'Lookup Tables'!$A$6:$B$14,2,0),"-") | G14: 46148 | H14: Medium | I14: Open | J14: 0 | N14: =IF(AND(I14<>"Closed",I14<>"On Hold",ISNUMBER(G14),TODAY()>G14),TODAY()-G14,"")
A15: ACT-012 | B15: Safety Mtg W17 | C15: 46134 | D15: Replace damaged scaffolding clips — Tag Red Zone 4 out of service immediately | E15: Scaffolding | F15: =IFERROR(VLOOKUP(E15,'Lookup Tables'!$A$6:$B$14,2,0),"-") | G15: 46136 | H15: Critical | I15: Closed | J15: 1 | K15: 46136 | L15: L. Andersen | N15: =IF(AND(I15<>"Closed",I15<>"On Hold",ISNUMBER(G15),TODAY()>G15),TODAY()-G15,"")
A16: ACT-013 | B16: Quality Mtg W17 | C16: 46136 | D16: Submit material traceability certificates for steel batch SB-044 | E16: Structural | F16: =IFERROR(VLOOKUP(E16,'Lookup Tables'!$A$6:$B$14,2,0),"-") | G16: 46140 | H16: High | I16: Closed | J16: 1 | K16: 46138 | L16: M. Berg | N16: =IF(AND(I16<>"Closed",I16<>"On Hold",ISNUMBER(G16),TODAY()>G16),TODAY()-G16,"")
A17: ACT-014 | B17: Site Coord W18 | C17: 46143 | D17: Validate instrument calibration data before loop testing | E17: Instrumentation | F17: =IFERROR(VLOOKUP(E17,'Lookup Tables'!$A$6:$B$14,2,0),"-") | G17: 46154 | H17: High | I17: Open | J17: 0 | N17: =IF(AND(I17<>"Closed",I17<>"On Hold",ISNUMBER(G17),TODAY()>G17),TODAY()-G17,"")
A18: ACT-015 | B18: Client Mtg W18 | C18: 46142 | D18: Confirm milestone dates — re-baseline if necessary; client sign-off required | E18: All | F18: =IFERROR(VLOOKUP(E18,'Lookup Tables'!$A$6:$B$14,2,0),"-") | G18: 46156 | H18: High | I18: Open | J18: 0 | N18: =IF(AND(I18<>"Closed",I18<>"On Hold",ISNUMBER(G18),TODAY()>G18),TODAY()-G18,"")
A19: ACT-016 | B19: Daily Standup W18 | C19: 46140 | D19: Resolve interface clash — mechanical skid vs. electrical conduit Zone A | E19: Mechanical | F19: =IFERROR(VLOOKUP(E19,'Lookup Tables'!$A$6:$B$14,2,0),"-") | G19: 46144 | H19: Medium | I19: In Progress | J19: 0.5 | L19: 3D review needed | N19: =IF(AND(I19<>"Closed",I19<>"On Hold",ISNUMBER(G19),TODAY()>G19),TODAY()-G19,"")
A20: ACT-017 | B20: Safety Mtg W18 | C20: 46141 | D20: Ensure all subcontractors complete updated Method Statement review | E20: All | F20: =IFERROR(VLOOKUP(E20,'Lookup Tables'!$A$6:$B$14,2,0),"-") | G20: 46148 | H20: High | I20: Open | J20: 0 | N20: =IF(AND(I20<>"Closed",I20<>"On Hold",ISNUMBER(G20),TODAY()>G20),TODAY()-G20,"")

Sheet NCR Quality Tracker
A1: NON-CONFORMANCE REPORT (NCR) & QUALITY TRACKER
A2: M (Days Open) = IF(Closed,0,TODAY()−DateRaised) · N (Discipline Lead) = INDEX/MATCH from Lookup Tables
A3: NCR No. | B3: Discipline | C3: Type | D3: Non-Conformance Description | E3: Location | F3: Raised By | G3: Date Raised | H3: Root Cause | I3: Corrective Action | J3: Responsible | K3: Due Date | L3: Status | M3: Days Open =TODAY()−raised | N3: Disc. Lead =INDEX/MATCH
A4: NCR-001 | B4: Structural | C4: Material | D4: Steel beam flange width 2mm below tolerance — spec 300mm, found 298mm | E4: Zone B Grid 5-6 | F4: M. Berg | G4: 46114 | H4: Wrong material ordered — spec not checked | I4: Replace beam; update procurement verification | J4: K. Lindqvist | K4: 46122 | L4: Closed | M4: =IF(L4="Closed",0,TODAY()-G4) | N4: =IFERROR(INDEX('Lookup Tables'!$B$6:$B$14,MATCH(B4,'Lookup Tables'!$A$6:$A$14,0)),"-")
A5: NCR-002 | B5: Civil | C5: Workmanship | D5: Concrete cover to rebar 18mm vs. 40mm specified | E5: Foundation B3 | F5: J. Hansen | G5: 46120 | H5: Formwork positioning error | I5: Break out and reinstate; supervisor sign-off | J5: J. Hansen | K5: 46130 | L5: Closed | M5: =IF(L5="Closed",0,TODAY()-G5) | N5: =IFERROR(INDEX('Lookup Tables'!$B$6:$B$14,MATCH(B5,'Lookup Tables'!$A$6:$A$14,0)),"-")
A6: NCR-003 | B6: Electrical | C6: Installation | D6: Cable tray support spacing 1200mm vs. 900mm per spec | E6: HV Room | F6: A. Nilsen | G6: 46124 | H6: Incorrect reading of installation spec | I6: Add intermediate supports; re-inspect all trays | J6: M. Berg | K6: 46134 | L6: Closed | M6: =IF(L6="Closed",0,TODAY()-G6) | N6: =IFERROR(INDEX('Lookup Tables'!$B$6:$B$14,MATCH(B6,'Lookup Tables'!$A$6:$A$14,0)),"-")
A7: NCR-004 | B7: Piping | C7: Workmanship | D7: Porosity defect in butt weld — Line P-101 Spool 4 | E7: Zone A Spool 4 | F7: S. Patel | G7: 46127 | H7: Welder qualification lapse; moisture in electrode | I7: Cut out and re-weld; 100% NDE on 2 adjacent | J7: S. Patel | K7: 46137 | L7: Closed | M7: =IF(L7="Closed",0,TODAY()-G7) | N7: =IFERROR(INDEX('Lookup Tables'!$B$6:$B$14,MATCH(B7,'Lookup Tables'!$A$6:$A$14,0)),"-")
A8: NCR-005 | B8: Structural | C8: Workmanship | D8: Bolt torque not achieved — beam-to-column Level 1 | E8: Building 1 L1 | F8: K. Lindqvist | G8: 46130 | H8: Torque wrench not calibrated | I8: Re-torque all; calibrate tools; 100% re-inspect | J8: K. Lindqvist | K8: 46140 | L8: Closed | M8: =IF(L8="Closed",0,TODAY()-G8) | N8: =IFERROR(INDEX('Lookup Tables'!$B$6:$B$14,MATCH(B8,'Lookup Tables'!$A$6:$A$14,0)),"-")
A9: NCR-006 | B9: HVAC | C9: Material | D9: Duct insulation 25mm vs. 40mm specified | E9: Building 1 L2 | F9: L. Andersen | G9: 46132 | H9: Incorrect material issued from stores | I9: Replace insulation; update material issue checklist | J9: L. Andersen | K9: 46143 | L9: In Progress | M9: =IF(L9="Closed",0,TODAY()-G9) | N9: =IFERROR(INDEX('Lookup Tables'!$B$6:$B$14,MATCH(B9,'Lookup Tables'!$A$6:$A$14,0)),"-")
A10: NCR-007 | B10: Structural | C10: Workmanship | D10: Incomplete fusion in fillet weld — Column C7 | E10: Zone C Col C7 | F10: M. Berg | G10: 46134 | H10: Welder fatigue and inadequate pre-heat | I10: Grind out and re-weld; PWHT review; briefing | J10: M. Berg | K10: 46147 | L10: In Progress | M10: =IF(L10="Closed",0,TODAY()-G10) | N10: =IFERROR(INDEX('Lookup Tables'!$B$6:$B$14,MATCH(B10,'Lookup Tables'!$A$6:$A$14,0)),"-")
A11: NCR-008 | B11: Civil | C11: Workmanship | D11: Backfill compaction 91% Proctor vs. 95% minimum | E11: Zone C Layer 3 | F11: J. Hansen | G11: 46137 | H11: Compaction plant breakdown — work continued | I11: Remove and re-compact; equipment check first | J11: J. Hansen | K11: 46149 | L11: Open | M11: =IF(L11="Closed",0,TODAY()-G11) | N11: =IFERROR(INDEX('Lookup Tables'!$B$6:$B$14,MATCH(B11,'Lookup Tables'!$A$6:$A$14,0)),"-")
A12: NCR-009 | B12: Mechanical | C12: Installation | D12: Pump alignment out of tolerance — axial 0.12mm vs. 0.05mm max | E12: Pump Hall P-203 | F12: A. Nilsen | G12: 46140 | H12: Grouting not cured before alignment | I12: Re-align after 28-day cure; document records | J12: A. Nilsen | K12: 46152 | L12: Open | M12: =IF(L12="Closed",0,TODAY()-G12) | N12: =IFERROR(INDEX('Lookup Tables'!$B$6:$B$14,MATCH(B12,'Lookup Tables'!$A$6:$A$14,0)),"-")
A13: NCR-010 | B13: Instrumentation | C13: Installation | D13: Wrong thermocouple type — type J installed vs. K specified | E13: Zone A TI-101 | F13: T. Eriksson | G13: 46141 | H13: Stores label incorrectly marked | I13: Replace with type K; audit all IDs site-wide | J13: T. Eriksson | K13: 46150 | L13: Open | M13: =IF(L13="Closed",0,TODAY()-G13) | N13: =IFERROR(INDEX('Lookup Tables'!$B$6:$B$14,MATCH(B13,'Lookup Tables'!$A$6:$A$14,0)),"-")
A14: NCR-011 | B14: Piping | C14: Workmanship | D14: Gasket material non-conformance — PTFE vs. spiral wound | E14: Zone A Flange F-22 | F14: S. Patel | G14: 46142 | H14: Substitution without engineering approval | I14: Replace gaskets; issue material deviation form | J14: S. Patel | K14: 46151 | L14: Open | M14: =IF(L14="Closed",0,TODAY()-G14) | N14: =IFERROR(INDEX('Lookup Tables'!$B$6:$B$14,MATCH(B14,'Lookup Tables'!$A$6:$A$14,0)),"-")
A15: NCR-012 | B15: Electrical | C15: Installation | D15: Conduit penetration unsealed — missing firestop in firewall | E15: Control Room | F15: M. Berg | G15: 46143 | H15: Subcontractor unaware of firewall requirement | I15: Apply approved firestop; inspect all penetrations | J15: M. Berg | K15: 46154 | L15: Open | M15: =IF(L15="Closed",0,TODAY()-G15) | N15: =IFERROR(INDEX('Lookup Tables'!$B$6:$B$14,MATCH(B15,'Lookup Tables'!$A$6:$A$14,0)),"-")

Sheet Monthly Report
A1: MONTHLY PROGRESS REPORT — Input & Earned Value Analysis
A2: Manual entry: A–H, K–M. Formula-driven: I (SV%) · J (CV%) · N (Disc. Lead = INDEX/MATCH). DASHBOARD SUMIFS pulls from cols A–H.
A3: Month | B3: Discipline | C3: Budget Hours | D3: Actual Hours | E3: Planned % | F3: Actual % | G3: Earned Value (NOK) | H3: Planned Value (NOK) | I3: Schedule Var % =IFERROR((F−E)/E,0) | J3: Cost Var % =IFERROR((G−H)/H,0) | K3: Key Milestones | L3: Issues | M3: Actions Raised | N3: Disc. Lead =INDEX/MATCH | O3: Forecast %
A4: Feb-26 | B4: Civil | C4: 1200 | D4: 1180 | E4: 0.3 | F4: 0.28 | G4: 168000 | H4: 180000 | I4: =IFERROR((F4-E4)/E4,0) | J4: =IFERROR((G4-H4)/H4,0) | K4: Excavation complete Zone A | L4: Soft ground — extra dewatering | M4: 0 | N4: =IFERROR(INDEX('Lookup Tables'!$B$6:$B$14,MATCH(B4,'Lookup Tables'!$A$6:$A$14,0)),"-") | O4: 0.34
A5: Feb-26 | B5: Structural | C5: 800 | D5: 790 | E5: 0.25 | F5: 0.26 | G5: 97500 | H5: 93750 | I5: =IFERROR((F5-E5)/E5,0) | J5: =IFERROR((G5-H5)/H5,0) | K5: Steel fabrication 100% complete | M5: 0 | N5: =IFERROR(INDEX('Lookup Tables'!$B$6:$B$14,MATCH(B5,'Lookup Tables'!$A$6:$A$14,0)),"-") | O5: 0.32
A6: Feb-26 | B6: Electrical | C6: 400 | D6: 380 | E6: 0.15 | F6: 0.14 | G6: 26600 | H6: 28000 | I6: =IFERROR((F6-E6)/E6,0) | J6: =IFERROR((G6-H6)/H6,0) | K6: Substation foundation ready | L6: Cable delivery delayed 1 week | M6: 2 | N6: =IFERROR(INDEX('Lookup Tables'!$B$6:$B$14,MATCH(B6,'Lookup Tables'!$A$6:$A$14,0)),"-") | O6: 0.2
A7: Mar-26 | B7: Civil | C7: 1400 | D7: 1450 | E7: 0.55 | F7: 0.53 | G7: 318000 | H7: 330000 | I7: =IFERROR((F7-E7)/E7,0) | J7: =IFERROR((G7-H7)/H7,0) | K7: Pile caps Zone A poured | L7: Formwork shortage — mitigated | M7: 1 | N7: =IFERROR(INDEX('Lookup Tables'!$B$6:$B$14,MATCH(B7,'Lookup Tables'!$A$6:$A$14,0)),"-") | O7: 0.59
A8: Mar-26 | B8: Structural | C8: 1200 | D8: 1150 | E8: 0.5 | F8: 0.52 | G8: 312000 | H8: 300000 | I8: =IFERROR((F8-E8)/E8,0) | J8: =IFERROR((G8-H8)/H8,0) | K8: Level 1 steel erection complete | M8: 1 | N8: =IFERROR(INDEX('Lookup Tables'!$B$6:$B$14,MATCH(B8,'Lookup Tables'!$A$6:$A$14,0)),"-") | O8: 0.58
A9: Mar-26 | B9: Electrical | C9: 600 | D9: 580 | E9: 0.3 | F9: 0.28 | G9: 84000 | H9: 90000 | I9: =IFERROR((F9-E9)/E9,0) | J9: =IFERROR((G9-H9)/H9,0) | K9: HV cable tray 60% installed | M9: 1 | N9: =IFERROR(INDEX('Lookup Tables'!$B$6:$B$14,MATCH(B9,'Lookup Tables'!$A$6:$A$14,0)),"-") | O9: 0.34
A10: Mar-26 | B10: Mechanical | C10: 500 | D10: 490 | E10: 0.25 | F10: 0.26 | G10: 65000 | H10: 62500 | I10: =IFERROR((F10-E10)/E10,0) | J10: =IFERROR((G10-H10)/H10,0) | K10: Pump skids P1–P4 set | M10: 0 | N10: =IFERROR(INDEX('Lookup Tables'!$B$6:$B$14,MATCH(B10,'Lookup Tables'!$A$6:$A$14,0)),"-") | O10: 0.32
A11: Mar-26 | B11: Piping | C11: 800 | D11: 820 | E11: 0.35 | F11: 0.38 | G11: 152000 | H11: 140000 | I11: =IFERROR((F11-E11)/E11,0) | J11: =IFERROR((G11-H11)/H11,0) | K11: Fabrication complete; inst. started | M11: 0 | N11: =IFERROR(INDEX('Lookup Tables'!$B$6:$B$14,MATCH(B11,'Lookup Tables'!$A$6:$A$14,0)),"-") | O11: 0.44
A12: Apr-26 | B12: Civil | C12: 1600 | D12: 1580 | E12: 0.72 | F12: 0.68 | G12: 408000 | H12: 432000 | I12: =IFERROR((F12-E12)/E12,0) | J12: =IFERROR((G12-H12)/H12,0) | K12: Zone B concrete pours started | L12: 2-day delay — road restrictions | M12: 3 | N12: =IFERROR(INDEX('Lookup Tables'!$B$6:$B$14,MATCH(B12,'Lookup Tables'!$A$6:$A$14,0)),"-") | O12: 0.74
A13: Apr-26 | B13: Structural | C13: 1400 | D13: 1390 | E13: 0.65 | F13: 0.7 | G13: 490000 | H13: 455000 | I13: =IFERROR((F13-E13)/E13,0) | J13: =IFERROR((G13-H13)/H13,0) | K13: Mezzanine steelwork in progress | M13: 0 | N13: =IFERROR(INDEX('Lookup Tables'!$B$6:$B$14,MATCH(B13,'Lookup Tables'!$A$6:$A$14,0)),"-") | O13: 0.76
A14: Apr-26 | B14: Electrical | C14: 900 | D14: 870 | E14: 0.55 | F14: 0.52 | G14: 234000 | H14: 247500 | I14: =IFERROR((F14-E14)/E14,0) | J14: =IFERROR((G14-H14)/H14,0) | K14: LV panel wiring started | L14: NCR on cable tray spacing | M14: 0 | N14: =IFERROR(INDEX('Lookup Tables'!$B$6:$B$14,MATCH(B14,'Lookup Tables'!$A$6:$A$14,0)),"-") | O14: 0.58
A15: Apr-26 | B15: Mechanical | C15: 700 | D15: 690 | E15: 0.48 | F15: 0.48 | G15: 168000 | H15: 168000 | I15: =IFERROR((F15-E15)/E15,0) | J15: =IFERROR((G15-H15)/H15,0) | K15: All pump equipment on site | L15: Alignment NCR P-203 | M15: 0 | N15: =IFERROR(INDEX('Lookup Tables'!$B$6:$B$14,MATCH(B15,'Lookup Tables'!$A$6:$A$14,0)),"-") | O15: 0.54
A16: Apr-26 | B16: Instrumentation | C16: 500 | D16: 490 | E16: 0.35 | F16: 0.33 | G16: 82500 | H16: 87500 | I16: =IFERROR((F16-E16)/E16,0) | J16: =IFERROR((G16-H16)/H16,0) | K16: Loop drawings reviewed — 80% | L16: Thermocouple type error | M16: 1 | N16: =IFERROR(INDEX('Lookup Tables'!$B$6:$B$14,MATCH(B16,'Lookup Tables'!$A$6:$A$14,0)),"-") | O16: 0.39
A17: Apr-26 | B17: Piping | C17: 1000 | D17: 980 | E17: 0.6 | F17: 0.62 | G17: 310000 | H17: 300000 | I17: =IFERROR((F17-E17)/E17,0) | J17: =IFERROR((G17-H17)/H17,0) | K17: Hydro test P-101 complete | M17: 1 | N17: =IFERROR(INDEX('Lookup Tables'!$B$6:$B$14,MATCH(B17,'Lookup Tables'!$A$6:$A$14,0)),"-") | O17: 0.68
A18: Apr-26 | B18: HVAC | C18: 600 | D18: 580 | E18: 0.4 | F18: 0.38 | G18: 114000 | H18: 120000 | I18: =IFERROR((F18-E18)/E18,0) | J18: =IFERROR((G18-H18)/H18,0) | K18: Ductwork 60% fabricated | L18: Duct insulation NCR | M18: 0 | N18: =IFERROR(INDEX('Lookup Tables'!$B$6:$B$14,MATCH(B18,'Lookup Tables'!$A$6:$A$14,0)),"-") | O18: 0.44
A19: Apr-26 | B19: Scaffolding | C19: 300 | D19: 295 | E19: 0.8 | F19: 0.82 | G19: 73800 | H19: 72000 | I19: =IFERROR((F19-E19)/E19,0) | J19: =IFERROR((G19-H19)/H19,0) | K19: All active scaffolding inspected | M19: 1 | N19: =IFERROR(INDEX('Lookup Tables'!$B$6:$B$14,MATCH(B19,'Lookup Tables'!$A$6:$A$14,0)),"-") | O19: 0.88
A22: MONTHLY EARNED VALUE ANALYSIS · Data sourced from DASHBOARD SUMIFS (cross-sheet reference)

Sheet Data Validation Log
A1: DATA VALIDATION & QUALITY LOG
A2: PURPOSE: Log all data quality issues found during weekly/monthly validation sweeps. Every anomaly must be logged before correction to maintain a full audit trail. All Open items must be resolved before submission to client reporting.
A4: Log ID | B4: Date Found | C4: Data Source | D4: Field / Column | E4: Error Type | F4: Error Description | G4: Responsible | H4: Severity | I4: Action Taken | J4: Status | K4: Date Resolved
A5: VAL-001 | B5: 46140 | C5: Weekly Progress | D5: Actual % | E5: Missing Data | F5: Actual % not entered for Instrumentation W17 | G5: T. Eriksson | H5: High | I5: Followed up; data entered same day | J5: Resolved | K5: 46140
A6: VAL-002 | B6: 46140 | C6: Risk Register | D6: Review Date | E6: Stale Data | F6: 6 risks with review date passed — not updated for 2+ weeks | G6: S. Patel | H6: Medium | I6: All owners notified; register updated W18 | J6: Resolved | K6: 46141
A7: VAL-003 | B7: 46141 | C7: Action Item Log | D7: Due Date | E7: Missing Data | F7: 3 actions with no due date assigned | G7: J. Hansen | H7: High | I7: Dates confirmed in coord meeting W18 | J7: Resolved | K7: 46141
A8: VAL-004 | B8: 46141 | C8: Monthly Report | D8: Actual Hours | E8: Out of Range | F8: HVAC actual hours 5200 entered (budget 600) — data entry error | G8: L. Andersen | H8: Critical | I8: Corrected to 580h; source timesheet confirmed | J8: Resolved | K8: 46142
A9: VAL-005 | B9: 46142 | C9: NCR Tracker | D9: Root Cause | E9: Missing Data | F9: NCR-008, 009, 010 missing root cause entries | G9: M. Berg | H9: Medium | I9: Root causes added after investigation reports | J9: Resolved | K9: 46143
A10: VAL-006 | B10: 46142 | C10: Weekly Progress | D10: Week No. | E10: Wrong Format | F10: Week entered as '18W' instead of integer 18 | G10: R. Kowalski | H10: Low | I10: Corrected; format reminder sent to all leads | J10: Resolved | K10: 46143
A11: VAL-007 | B11: 46143 | C11: Monthly Report | D11: EV Calc | E11: Logic Error | F11: Earned Value = −12000 for Piping Feb-26 — formula error | G11: S. Patel | H11: High | I11: Formula corrected; cross-checked against cost plan | J11: Resolved | K11: 46143
A12: VAL-008 | B12: 46144 | C12: Action Item Log | D12: Status | E12: Stale Data | F12: 4 actions marked Open with due date passed | G12: J. Hansen | H12: High | I12: Status updated to Overdue; owners notified | J12: Resolved | K12: 46144
A13: VAL-009 | B13: 46145 | C13: Risk Register | D13: Risk Score | E13: Logic Error | F13: RSK-006 score = 0 — Probability and Impact were blank | G13: S. Patel | H13: Medium | I13: Values entered; level updated to Medium (score = 8) | J13: Resolved | K13: 46145
A14: VAL-010 | B14: 46146 | C14: Weekly Progress | D14: Responsible | E14: Missing Data | F14: 2 activities have no Responsible person assigned | G14: J. Hansen | H14: Medium | I14: XLOOKUP auto-filled; manual review pending | J14: Open
A15: VAL-011 | B15: 46146 | C15: NCR Tracker | D15: Date Closed | E15: Logic Error | F15: NCR-006 status=Closed but Date Closed cell is empty | G15: M. Berg | H15: High | I15: Correction in progress | J15: Open
A16: VAL-012 | B16: 46146 | C16: Monthly Report | D16: Forecast % | E16: Out of Range | F16: Forecast 112% for Civil Apr-26 — cannot exceed 100% | G16: J. Hansen | H16: Medium | I16: Capped at 100%; formula review in progress | J16: Open

Sheet Lookup Tables
A1: LOOKUP TABLES — Reference Data for Formula Calculations
A2: Powers VLOOKUP · XLOOKUP · INDEX/MATCH across all sheets. Do not rename or delete this sheet.
A4: TABLE 1 · Discipline → Lead Person (VLOOKUP / XLOOKUP / INDEX-MATCH reference) | F4: TABLE 2 · Risk Score Reference (IFS formula band reference)
A5: Discipline | B5: Lead Person | C5: Dept. Code | D5: Email | F5: Min Score | G5: Max Score | H5: Level | I5: SLA Response
A6: Civil | B6: J. Hansen | C6: CIV | D6: j.hansen@project.com | F6: 15 | G6: 25 | H6: High | I6: Immediate action
A7: Structural | B7: K. Lindqvist | C7: STR | D7: k.lindqvist@project.com | F7: 8 | G7: 14 | H7: Medium | I7: Action within 14 days
A8: Electrical | B8: M. Berg | C8: ELE | D8: m.berg@project.com | F8: 1 | G8: 7 | H8: Low | I8: Monitor monthly
A9: Mechanical | B9: A. Nilsen | C9: MEC | D9: a.nilsen@project.com
A10: Instrumentation | B10: T. Eriksson | C10: INS | D10: t.eriksson@project.com
A11: Piping | B11: S. Patel | C11: PIP | D11: s.patel@project.com
A12: HVAC | B12: L. Andersen | C12: HVA | D12: l.andersen@project.com
A13: Scaffolding | B13: R. Kowalski | C13: SCA | D13: r.kowalski@project.com
A14: All | B14: J. Hansen | C14: ALL | D14: j.hansen@project.com
A16: TABLE 3 · Status Definitions & Dropdown Values | F16: TABLE 4 · Formula Index — Where Each Advanced Function Is Used
A17: Status | B17: Applies To | C17: Final? | D17: Description | F17: Sheet | G17: Column | H17: Function | I17: Purpose
A18: Open | B18: Actions / Risks / NCRs | C18: No | D18: Raised, no action started | F18: Weekly Progress | G18: Variance % | H18: =H-G | I18: Auto variance
A19: In Progress | B19: Actions / NCRs | C19: No | D19: Work underway | F19: Weekly Progress | G19: Status | H19: IF nested | I19: Auto status logic
A20: Closed | B20: All | C20: Yes | D20: Fully resolved and verified | F20: Weekly Progress | G20: Responsible | H20: XLOOKUP | I20: From Lookup Tables
A21: Overdue | B21: Actions | C21: No | D21: Past due date — escalate | F21: Risk Register | G21: Risk Score | H21: =E×F | I21: Auto P×I
A22: Escalated | B22: Risks | C22: No | D22: Elevated to senior management | F22: Risk Register | G22: Risk Level | H22: IF nested | I22: From score
A23: Mitigated | B23: Risks | C23: No | D23: Mitigation complete; monitoring | F23: Action Item Log | G23: Responsible | H23: VLOOKUP | I23: From Lookup Tables
A24: On Hold | B24: Actions | C24: No | D24: Blocked — awaiting input | F24: Action Item Log | G24: Days Overdue | H24: IF/TODAY() | I24: Live days past due
F25: NCR Tracker | G25: Days Open | H25: IF/TODAY() | I25: Live days since raised
F26: NCR Tracker | G26: Discipline Lead | H26: INDEX/MATCH | I26: From Lookup Tables
F27: Monthly Report | G27: Schedule Var % | H27: IFERROR/() | I27: Auto SV%
F28: Monthly Report | G28: Cost Var % | H28: IFERROR/() | I28: Auto CV%
F29: Monthly Report | G29: Discipline Lead | H29: INDEX/MATCH | I29: From Lookup Tables
F30: DASHBOARD | G30: All KPIs | H30: COUNTIF | I30: Live from data sheets
F31: DASHBOARD | G31: Discipline table | H31: AVERAGEIF | I31: Live pull per discipline
F32: DASHBOARD | G32: Monthly summary | H32: SUMIFS | I32: Multi-criteria totals

Sheet Instructions & Guide
A1: WORKBOOK GUIDE — Construction Project Data Management System
A2: Sheet directory, formula reference, color legend, ID conventions, and usage workflow.
A4: SHEET DIRECTORY
A5: Sheet | B5: Purpose | C5: Entry Columns | D5: Key Formulas | E5: Update Frequency
A6: Lookup Tables | B6: Reference tables — powers all lookup formulas | C6: Update when personnel changes | D6: N/A | E6: When team changes
A7: DASHBOARD | B7: Live project health — KPIs, progress, risk, actions, EV | C7: Read-only (formula-driven) | D7: COUNTIF/S, AVERAGEIF, SUMIFS | E7: Auto on file open
A8: Weekly Progress | B8: Planned vs. actual % per activity per week | C8: G (Planned%) and H (Actual%) | D8: IF, XLOOKUP | E8: Weekly — by Friday
A9: Risk Register | B9: Risk log with P×I matrix and auto level | C9: All except G, H | D9: E×F, nested IF | E9: Weekly minimum
A10: Action Item Log | B10: All meeting action items with status tracking | C10: All except F, N | D10: VLOOKUP, IF/TODAY() | E10: After each meeting
A11: NCR Quality Tracker | B11: Non-conformance full lifecycle | C11: All except M, N | D11: TODAY()−date, INDEX/MATCH | E11: As NCRs arise
A12: Monthly Report | B12: Budget vs. actual + Earned Value analysis | C12: A–H, K–M | D12: SV/CV formulas, INDEX/MATCH, SUMIFS | E12: 2nd working day
A13: Data Validation Log | B13: Data quality issues audit trail | C13: All columns | D13: Manual log | E13: During validation sweep
A16: FORMULA REFERENCE
A17: Function | B17: Sheet — Column | C17: Example | D17: Purpose | E17: Version
A18: COUNTIF | B18: Dashboard — KPI tiles | C18: =COUNTIF($I:$I,"Open") | D18: Count matching single criterion | E18: All
A19: COUNTIFS | B19: Dashboard — discipline table | C19: =COUNTIFS($E:$E,"Civil",$I:$I,"Open") | D19: Count matching multiple criteria | E19: 2007+
A20: AVERAGEIF | B20: Dashboard — discipline % | C20: =AVERAGEIF($B:$B,"Civil",$H:$H) | D20: Average matching one criterion | E20: 2007+
A21: SUMIFS | B21: Dashboard — monthly summary | C21: =SUMIFS($C:$C,$A:$A,"Apr-26") | D21: Sum matching multiple criteria | E21: 2007+
A22: VLOOKUP | B22: Action Log — Responsible col | C22: =IFERROR(VLOOKUP(E3,$A$6:$B$14,2,0),"-") | D22: Lookup value in first column of table | E22: All
A23: XLOOKUP | B23: Weekly Progress — Responsible | C23: =IFERROR(XLOOKUP(B3,$A$6:$A$14,$B$6:$B$14),"?") | D23: Flexible; searches any direction | E23: Excel 365
A24: INDEX/MATCH | B24: NCR & Monthly — Disc. Lead | C24: =INDEX($B$6:$B$14,MATCH(B3,$A$6:$A$14,0)) | D24: Flexible alternative to VLOOKUP | E24: All
A25: IF nested | B25: Weekly Progress — Status col | C25: =IF(H3>=1,"Completed",IF(...)) | D25: Multi-branch conditional logic | E25: All
A26: IFERROR | B26: All formula columns | C26: =IFERROR(formula,0) | D26: Return fallback if formula errors | E26: 2007+
A27: TODAY() | B27: Action Log — Days Overdue | C27: =IF(AND(I3<>"Closed",TODAY()>G3),TODAY()-G3,"") | D27: Current date; updates on open | E27: All
A30: COLOR & BADGE LEGEND
B31: Green badge | C31: Completed · Closed · Resolved · Ahead · Low risk
B32: Blue badge | C32: Open · On Track · Mitigated · Material
B33: Amber badge | C33: In Progress · Medium · Workmanship · Warning
B34: Red badge | C34: Overdue · High · Behind · Critical · Escalated
B35: Gray badge | C35: Not Started · On Hold · Neutral / N/A
B36: Teal badge | C36: Installation type NCRs
B37: Surface row | C37: Alternating data row background (barely visible)
B38: Dark header | C38: Column headers and section headers — uniform charcoal
B39: Ink title | C39: Sheet titles — near-black
